{"chunk_definitions":[{"chunk_id":"csetup_chunk","chunk_label":"setup","document_id":"86605264","expansion_state":0,"options":{"engine":"r","include":false,"label":"setup"},"row":11,"row_count":1,"visible":true},{"chunk_id":"cvyory6x11bzx","chunk_label":"unnamed-chunk-1","document_id":"86605264","expansion_state":0,"options":{"engine":"r","label":"unnamed-chunk-4"},"row":19,"row_count":1,"visible":true},{"chunk_id":"cxhh9itndf44l","chunk_label":"unnamed-chunk-2","document_id":"86605264","expansion_state":0,"options":{"engine":"r","label":"unnamed-chunk-6"},"row":27,"row_count":1,"visible":true},{"chunk_id":"cmc5hfa0t22d0","chunk_label":"unnamed-chunk-3","document_id":"86605264","expansion_state":0,"options":{"engine":"r","label":"unnamed-chunk-9"},"row":38,"row_count":1,"visible":true},{"chunk_id":"cx6h06yqmm55i","chunk_label":"unnamed-chunk-4","document_id":"86605264","expansion_state":0,"options":{"engine":"r","label":"unnamed-chunk-13"},"row":47,"row_count":1,"visible":true},{"chunk_id":"cytjty3gf39dy","chunk_label":"unnamed-chunk-5","document_id":"86605264","expansion_state":0,"options":{"engine":"r","label":"unnamed-chunk-16"},"row":54,"row_count":1,"visible":true},{"chunk_id":"chiailtrv6e1g","chunk_label":"unnamed-chunk-6","document_id":"86605264","expansion_state":0,"options":{"engine":"r","label":"unnamed-chunk-18"},"row":60,"row_count":1,"visible":true},{"chunk_id":"cg7a604b24ruy","chunk_label":"unnamed-chunk-7","document_id":"86605264","expansion_state":0,"options":{"engine":"r","label":"unnamed-chunk-26"},"row":67,"row_count":1,"visible":true},{"chunk_id":"chkwgf472uw34","chunk_label":"unnamed-chunk-8","document_id":"86605264","expansion_state":0,"options":{"engine":"r","label":"unnamed-chunk-27"},"row":71,"row_count":1,"visible":true},{"chunk_id":"cbiq03f547msz","chunk_label":"unnamed-chunk-9","document_id":"86605264","expansion_state":0,"options":{"engine":"r","label":"unnamed-chunk-28"},"row":75,"row_count":1,"visible":true}],"default_chunk_options":{"error":false},"doc_write_time":8296874535683646303,"working_dir":null}